[
  { "R": 255, "G": 255, "B": 255, "A": 0 },
  { "R": 255, "G": 255, "B": 204, "A": 0 },
  { "R": 255, "G": 255, "B": 153, "A": 0 },
  { "R": 255, "G": 255, "B": 102, "A": 0 },
  { "R": 255, "G": 255, "B": 51, "A": 0 },
  { "R": 255, "G": 255, "B": 0, "A": 0 },
  { "R": 255, "G": 204, "B": 255, "A": 0 },
  { "R": 255, "G": 204, "B": 204, "A": 0 },
  { "R": 255, "G": 204, "B": 153, "A": 0 },
  { "R": 255, "G": 204, "B": 102, "A": 0 },
  { "R": 255, "G": 204, "B": 51, "A": 0 },
  { "R": 255, "G": 204, "B": 0, "A": 0 },
  { "R": 255, "G": 153, "B": 255, "A": 0 },
  { "R": 255, "G": 153, "B": 204, "A": 0 },
  { "R": 255, "G": 153, "B": 153, "A": 0 },
  { "R": 255, "G": 153, "B": 102, "A": 0 },
  { "R": 255, "G": 153, "B": 51, "A": 0 },
  { "R": 255, "G": 153, "B": 0, "A": 0 },
  { "R": 255, "G": 102, "B": 255, "A": 0 },
  { "R": 255, "G": 102, "B": 204, "A": 0 },
  { "R": 255, "G": 102, "B": 153, "A": 0 },
  { "R": 255, "G": 102, "B": 102, "A": 0 },
  { "R": 255, "G": 102, "B": 51, "A": 0 },
  { "R": 255, "G": 102, "B": 0, "A": 0 },
  { "R": 255, "G": 51, "B": 255, "A": 0 },
  { "R": 255, "G": 51, "B": 204, "A": 0 },
  { "R": 255, "G": 51, "B": 153, "A": 0 },
  { "R": 255, "G": 51, "B": 102, "A": 0 },
  { "R": 255, "G": 51, "B": 51, "A": 0 },
  { "R": 255, "G": 51, "B": 0, "A": 0 },
  { "R": 255, "G": 0, "B": 255, "A": 0 },
  { "R": 255, "G": 0, "B": 204, "A": 0 },
  { "R": 255, "G": 0, "B": 153, "A": 0 },
  { "R": 255, "G": 0, "B": 102, "A": 0 },
  { "R": 255, "G": 0, "B": 51, "A": 0 },
  { "R": 255, "G": 0, "B": 0, "A": 0 },
  { "R": 204, "G": 255, "B": 255, "A": 0 },
  { "R": 204, "G": 255, "B": 204, "A": 0 },
  { "R": 204, "G": 255, "B": 153, "A": 0 },
  { "R": 204, "G": 255, "B": 102, "A": 0 },
  { "R": 204, "G": 255, "B": 51, "A": 0 },
  { "R": 204, "G": 255, "B": 0, "A": 0 },
  { "R": 204, "G": 204, "B": 255, "A": 0 },
  { "R": 204, "G": 204, "B": 204, "A": 0 },
  { "R": 204, "G": 204, "B": 153, "A": 0 },
  { "R": 204, "G": 204, "B": 102, "A": 0 },
  { "R": 204, "G": 204, "B": 51, "A": 0 },
  { "R": 204, "G": 204, "B": 0, "A": 0 },
  { "R": 204, "G": 153, "B": 255, "A": 0 },
  { "R": 204, "G": 153, "B": 204, "A": 0 },
  { "R": 204, "G": 153, "B": 153, "A": 0 },
  { "R": 204, "G": 153, "B": 102, "A": 0 },
  { "R": 204, "G": 153, "B": 51, "A": 0 },
  { "R": 204, "G": 153, "B": 0, "A": 0 },
  { "R": 204, "G": 102, "B": 255, "A": 0 },
  { "R": 204, "G": 102, "B": 204, "A": 0 },
  { "R": 204, "G": 102, "B": 153, "A": 0 },
  { "R": 204, "G": 102, "B": 102, "A": 0 },
  { "R": 204, "G": 102, "B": 51, "A": 0 },
  { "R": 204, "G": 102, "B": 0, "A": 0 },
  { "R": 204, "G": 51, "B": 255, "A": 0 },
  { "R": 204, "G": 51, "B": 204, "A": 0 },
  { "R": 204, "G": 51, "B": 153, "A": 0 },
  { "R": 204, "G": 51, "B": 102, "A": 0 },
  { "R": 204, "G": 51, "B": 51, "A": 0 },
  { "R": 204, "G": 51, "B": 0, "A": 0 },
  { "R": 204, "G": 0, "B": 255, "A": 0 },
  { "R": 204, "G": 0, "B": 204, "A": 0 },
  { "R": 204, "G": 0, "B": 153, "A": 0 },
  { "R": 204, "G": 0, "B": 102, "A": 0 },
  { "R": 204, "G": 0, "B": 51, "A": 0 },
  { "R": 204, "G": 0, "B": 0, "A": 0 },
  { "R": 153, "G": 255, "B": 255, "A": 0 },
  { "R": 153, "G": 255, "B": 204, "A": 0 },
  { "R": 153, "G": 255, "B": 153, "A": 0 },
  { "R": 153, "G": 255, "B": 102, "A": 0 },
  { "R": 153, "G": 255, "B": 51, "A": 0 },
  { "R": 153, "G": 255, "B": 0, "A": 0 },
  { "R": 153, "G": 204, "B": 255, "A": 0 },
  { "R": 153, "G": 204, "B": 204, "A": 0 },
  { "R": 153, "G": 204, "B": 153, "A": 0 },
  { "R": 153, "G": 204, "B": 102, "A": 0 },
  { "R": 153, "G": 204, "B": 51, "A": 0 },
  { "R": 153, "G": 204, "B": 0, "A": 0 },
  { "R": 153, "G": 153, "B": 255, "A": 0 },
  { "R": 153, "G": 153, "B": 204, "A": 0 },
  { "R": 153, "G": 153, "B": 153, "A": 0 },
  { "R": 153, "G": 153, "B": 102, "A": 0 },
  { "R": 153, "G": 153, "B": 51, "A": 0 },
  { "R": 153, "G": 153, "B": 0, "A": 0 },
  { "R": 153, "G": 102, "B": 255, "A": 0 },
  { "R": 153, "G": 102, "B": 204, "A": 0 },
  { "R": 153, "G": 102, "B": 153, "A": 0 },
  { "R": 153, "G": 102, "B": 102, "A": 0 },
  { "R": 153, "G": 102, "B": 51, "A": 0 },
  { "R": 153, "G": 102, "B": 0, "A": 0 },
  { "R": 153, "G": 51, "B": 255, "A": 0 },
  { "R": 153, "G": 51, "B": 204, "A": 0 },
  { "R": 153, "G": 51, "B": 153, "A": 0 },
  { "R": 153, "G": 51, "B": 102, "A": 0 },
  { "R": 153, "G": 51, "B": 51, "A": 0 },
  { "R": 153, "G": 51, "B": 0, "A": 0 },
  { "R": 153, "G": 0, "B": 255, "A": 0 },
  { "R": 153, "G": 0, "B": 204, "A": 0 },
  { "R": 153, "G": 0, "B": 153, "A": 0 },
  { "R": 153, "G": 0, "B": 102, "A": 0 },
  { "R": 153, "G": 0, "B": 51, "A": 0 },
  { "R": 153, "G": 0, "B": 0, "A": 0 },
  { "R": 102, "G": 255, "B": 255, "A": 0 },
  { "R": 102, "G": 255, "B": 204, "A": 0 },
  { "R": 102, "G": 255, "B": 153, "A": 0 },
  { "R": 102, "G": 255, "B": 102, "A": 0 },
  { "R": 102, "G": 255, "B": 51, "A": 0 },
  { "R": 102, "G": 255, "B": 0, "A": 0 },
  { "R": 102, "G": 204, "B": 255, "A": 0 },
  { "R": 102, "G": 204, "B": 204, "A": 0 },
  { "R": 102, "G": 204, "B": 153, "A": 0 },
  { "R": 102, "G": 204, "B": 102, "A": 0 },
  { "R": 102, "G": 204, "B": 51, "A": 0 },
  { "R": 102, "G": 204, "B": 0, "A": 0 },
  { "R": 102, "G": 153, "B": 255, "A": 0 },
  { "R": 102, "G": 153, "B": 204, "A": 0 },
  { "R": 102, "G": 153, "B": 153, "A": 0 },
  { "R": 102, "G": 153, "B": 102, "A": 0 },
  { "R": 102, "G": 153, "B": 51, "A": 0 },
  { "R": 102, "G": 153, "B": 0, "A": 0 },
  { "R": 102, "G": 102, "B": 255, "A": 0 },
  { "R": 102, "G": 102, "B": 204, "A": 0 },
  { "R": 102, "G": 102, "B": 153, "A": 0 },
  { "R": 102, "G": 102, "B": 102, "A": 0 },
  { "R": 102, "G": 102, "B": 51, "A": 0 },
  { "R": 102, "G": 102, "B": 0, "A": 0 },
  { "R": 102, "G": 51, "B": 255, "A": 0 },
  { "R": 102, "G": 51, "B": 204, "A": 0 },
  { "R": 102, "G": 51, "B": 153, "A": 0 },
  { "R": 102, "G": 51, "B": 102, "A": 0 },
  { "R": 102, "G": 51, "B": 51, "A": 0 },
  { "R": 102, "G": 51, "B": 0, "A": 0 },
  { "R": 102, "G": 0, "B": 255, "A": 0 },
  { "R": 102, "G": 0, "B": 204, "A": 0 },
  { "R": 102, "G": 0, "B": 153, "A": 0 },
  { "R": 102, "G": 0, "B": 102, "A": 0 },
  { "R": 102, "G": 0, "B": 51, "A": 0 },
  { "R": 102, "G": 0, "B": 0, "A": 0 },
  { "R": 51, "G": 255, "B": 255, "A": 0 },
  { "R": 51, "G": 255, "B": 204, "A": 0 },
  { "R": 51, "G": 255, "B": 153, "A": 0 },
  { "R": 51, "G": 255, "B": 102, "A": 0 },
  { "R": 51, "G": 255, "B": 51, "A": 0 },
  { "R": 51, "G": 255, "B": 0, "A": 0 },
  { "R": 51, "G": 204, "B": 255, "A": 0 },
  { "R": 51, "G": 204, "B": 204, "A": 0 },
  { "R": 51, "G": 204, "B": 153, "A": 0 },
  { "R": 51, "G": 204, "B": 102, "A": 0 },
  { "R": 51, "G": 204, "B": 51, "A": 0 },
  { "R": 51, "G": 204, "B": 0, "A": 0 },
  { "R": 51, "G": 153, "B": 255, "A": 0 },
  { "R": 51, "G": 153, "B": 204, "A": 0 },
  { "R": 51, "G": 153, "B": 153, "A": 0 },
  { "R": 51, "G": 153, "B": 102, "A": 0 },
  { "R": 51, "G": 153, "B": 51, "A": 0 },
  { "R": 51, "G": 153, "B": 0, "A": 0 },
  { "R": 51, "G": 102, "B": 255, "A": 0 },
  { "R": 51, "G": 102, "B": 204, "A": 0 },
  { "R": 51, "G": 102, "B": 153, "A": 0 },
  { "R": 51, "G": 102, "B": 102, "A": 0 },
  { "R": 51, "G": 102, "B": 51, "A": 0 },
  { "R": 51, "G": 102, "B": 0, "A": 0 },
  { "R": 51, "G": 51, "B": 255, "A": 0 },
  { "R": 51, "G": 51, "B": 204, "A": 0 },
  { "R": 51, "G": 51, "B": 153, "A": 0 },
  { "R": 51, "G": 51, "B": 102, "A": 0 },
  { "R": 51, "G": 51, "B": 51, "A": 0 },
  { "R": 51, "G": 51, "B": 0, "A": 0 },
  { "R": 51, "G": 0, "B": 255, "A": 0 },
  { "R": 51, "G": 0, "B": 204, "A": 0 },
  { "R": 51, "G": 0, "B": 153, "A": 0 },
  { "R": 51, "G": 0, "B": 102, "A": 0 },
  { "R": 51, "G": 0, "B": 51, "A": 0 },
  { "R": 51, "G": 0, "B": 0, "A": 0 },
  { "R": 0, "G": 255, "B": 255, "A": 0 },
  { "R": 0, "G": 255, "B": 204, "A": 0 },
  { "R": 0, "G": 255, "B": 153, "A": 0 },
  { "R": 0, "G": 255, "B": 102, "A": 0 },
  { "R": 0, "G": 255, "B": 51, "A": 0 },
  { "R": 0, "G": 255, "B": 0, "A": 0 },
  { "R": 0, "G": 204, "B": 255, "A": 0 },
  { "R": 0, "G": 204, "B": 204, "A": 0 },
  { "R": 0, "G": 204, "B": 153, "A": 0 },
  { "R": 0, "G": 204, "B": 102, "A": 0 },
  { "R": 0, "G": 204, "B": 51, "A": 0 },
  { "R": 0, "G": 204, "B": 0, "A": 0 },
  { "R": 0, "G": 153, "B": 255, "A": 0 },
  { "R": 0, "G": 153, "B": 204, "A": 0 },
  { "R": 0, "G": 153, "B": 153, "A": 0 },
  { "R": 0, "G": 153, "B": 102, "A": 0 },
  { "R": 0, "G": 153, "B": 51, "A": 0 },
  { "R": 0, "G": 153, "B": 0, "A": 0 },
  { "R": 0, "G": 102, "B": 255, "A": 0 },
  { "R": 0, "G": 102, "B": 204, "A": 0 },
  { "R": 0, "G": 102, "B": 153, "A": 0 },
  { "R": 0, "G": 102, "B": 102, "A": 0 },
  { "R": 0, "G": 102, "B": 51, "A": 0 },
  { "R": 0, "G": 102, "B": 0, "A": 0 },
  { "R": 0, "G": 51, "B": 255, "A": 0 },
  { "R": 0, "G": 51, "B": 204, "A": 0 },
  { "R": 0, "G": 51, "B": 153, "A": 0 },
  { "R": 0, "G": 51, "B": 102, "A": 0 },
  { "R": 0, "G": 51, "B": 51, "A": 0 },
  { "R": 0, "G": 51, "B": 0, "A": 0 },
  { "R": 0, "G": 0, "B": 255, "A": 0 },
  { "R": 0, "G": 0, "B": 204, "A": 0 },
  { "R": 0, "G": 0, "B": 153, "A": 0 },
  { "R": 0, "G": 0, "B": 102, "A": 0 },
  { "R": 0, "G": 0, "B": 51, "A": 0 },
  { "R": 238, "G": 0, "B": 0, "A": 0 },
  { "R": 221, "G": 0, "B": 0, "A": 0 },
  { "R": 187, "G": 0, "B": 0, "A": 0 },
  { "R": 170, "G": 0, "B": 0, "A": 0 },
  { "R": 136, "G": 0, "B": 0, "A": 0 },
  { "R": 119, "G": 0, "B": 0, "A": 0 },
  { "R": 85, "G": 0, "B": 0, "A": 0 },
  { "R": 68, "G": 0, "B": 0, "A": 0 },
  { "R": 34, "G": 0, "B": 0, "A": 0 },
  { "R": 17, "G": 0, "B": 0, "A": 0 },
  { "R": 0, "G": 238, "B": 0, "A": 0 },
  { "R": 0, "G": 221, "B": 0, "A": 0 },
  { "R": 0, "G": 187, "B": 0, "A": 0 },
  { "R": 0, "G": 170, "B": 0, "A": 0 },
  { "R": 0, "G": 136, "B": 0, "A": 0 },
  { "R": 0, "G": 119, "B": 0, "A": 0 },
  { "R": 0, "G": 85, "B": 0, "A": 0 },
  { "R": 0, "G": 68, "B": 0, "A": 0 },
  { "R": 0, "G": 34, "B": 0, "A": 0 },
  { "R": 0, "G": 17, "B": 0, "A": 0 },
  { "R": 0, "G": 0, "B": 238, "A": 0 },
  { "R": 0, "G": 0, "B": 221, "A": 0 },
  { "R": 0, "G": 0, "B": 187, "A": 0 },
  { "R": 0, "G": 0, "B": 170, "A": 0 },
  { "R": 0, "G": 0, "B": 136, "A": 0 },
  { "R": 0, "G": 0, "B": 119, "A": 0 },
  { "R": 0, "G": 0, "B": 85, "A": 0 },
  { "R": 0, "G": 0, "B": 68, "A": 0 },
  { "R": 0, "G": 0, "B": 34, "A": 0 },
  { "R": 0, "G": 0, "B": 17, "A": 0 },
  { "R": 238, "G": 238, "B": 238, "A": 0 },
  { "R": 221, "G": 221, "B": 221, "A": 0 },
  { "R": 187, "G": 187, "B": 187, "A": 0 },
  { "R": 170, "G": 170, "B": 170, "A": 0 },
  { "R": 136, "G": 136, "B": 136, "A": 0 },
  { "R": 119, "G": 119, "B": 119, "A": 0 },
  { "R": 85, "G": 85, "B": 85, "A": 0 },
  { "R": 68, "G": 68, "B": 68, "A": 0 },
  { "R": 34, "G": 34, "B": 34, "A": 0 },
  { "R": 17, "G": 17, "B": 17, "A": 0 },
  { "R": 0, "G": 0, "B": 0, "A": 0 }
]
